app_creator/__init__.py
app_creator/cli.py
keita/__init__.py
keita/admin.py
keita/apps.py
keita/tests.py
keita/urls.py
keita/migrations/__init__.py
keita/models/__init__.py
keita/views/__init__.py
migrations/__init__.py
models/__init__.py
views/__init__.py
keith_django_app_creator-0.8.0.dist-info/METADATA
keith_django_app_creator-0.8.0.dist-info/WHEEL
keith_django_app_creator-0.8.0.dist-info/entry_points.txt
keith_django_app_creator-0.8.0.dist-info/top_level.txt
keith_django_app_creator-0.8.0.dist-info/RECORD
