Metadata-Version: 2.4
Name: keith-django-app-creator
Version: 0.8.0
Summary: Générateur de structure d'app Django personnalisée
Author: Keith44
Author-email: keitamohamed1432@gmail.com
License: MIT
Classifier: Programming Language :: Python :: 3
Classifier: Framework :: Django
Classifier: License :: OSI Approved :: MIT License
Dynamic: author
Dynamic: author-email
Dynamic: classifier
Dynamic: description
Dynamic: description-content-type
Dynamic: license
Dynamic: summary
